pyring/__init__.py
pyring/disruptor.py
pyring/exceptions.py
pyring/py.typed
pyring/ring_buffer.py
pyring/ring_factory.py
tests/__init__.py
tests/test_blocking_ring_buffer.py
tests/test_ring_buffer.py
tests/test_ring_factory.py
tests/test_single_producer_disruptor.py
tests/test_waiting_blocking_ring_buffer.py
pyring-0.0.12.dist-info/LICENCE
pyring-0.0.12.dist-info/METADATA
pyring-0.0.12.dist-info/WHEEL
pyring-0.0.12.dist-info/top_level.txt
pyring-0.0.12.dist-info/RECORD
