Metadata-Version: 2.1
Name: pyring
Version: 0.0.12
Summary: A ring buffer (circular buffer, circular queue, cyclic buffer) implemented in pure python. Includes flexible locking, waiting, and Disruptor variants.
Home-page: https://github.com/jaycosaur/pyring
Author: Jacob Richter
Author-email: jaycorichter@gmail.com
License: UNKNOWN
Platform: UNKNOWN
Classifier: Programming Language :: Python :: 3
Classifier: License :: OSI Approved :: MIT License
Classifier: Operating System :: OS Independent
